cli/__init__.py
cli/build.py
fico/__about__.py
fico/__init__.py
fico/building.py
fico/figure.py
fico/styling.py
fico/utils.py
fico/styles/eit6_publication.mplstyle
fico/templates/basic_table.tex
fico-0.1.1.dist-info/METADATA
fico-0.1.1.dist-info/WHEEL
fico-0.1.1.dist-info/entry_points.txt
fico-0.1.1.dist-info/licenses/LICENSE
fico-0.1.1.dist-info/RECORD
