Metadata-Version: 2.1
Name: fico
Version: 0.1.1
Summary: Build tool for creating Matplotlib figures with sensible defaults that look native in LaTeX-documents.
Author: Markus Ellyton
License: MIT License
License-File: LICENSE
Requires-Python: >3.8
Requires-Dist: matplotlib
Requires-Dist: termcolor
Provides-Extra: tables
Requires-Dist: jinja2; extra == 'tables'
